cogsol/__init__.py
cogsol/prompts.py
cogsol/agents/__init__.py
cogsol/bin/__init__.py
cogsol/bin/cogsol_admin.py
cogsol/content/__init__.py
cogsol/core/__init__.py
cogsol/core/api.py
cogsol/core/env.py
cogsol/core/loader.py
cogsol/core/management.py
cogsol/core/migrations.py
cogsol/db/__init__.py
cogsol/db/migrations.py
cogsol/management/__init__.py
cogsol/management/base.py
cogsol/management/commands/__init__.py
cogsol/management/commands/chat.py
cogsol/management/commands/importagent.py
cogsol/management/commands/ingest.py
cogsol/management/commands/makemigrations.py
cogsol/management/commands/migrate.py
cogsol/management/commands/startagent.py
cogsol/management/commands/startproject.py
cogsol/management/commands/starttopic.py
cogsol/management/commands/topics.py
cogsol/tools/__init__.py
cogsol_framework-0.2.0.dist-info/licenses/LICENSE
cogsol_framework-0.2.0.dist-info/METADATA
cogsol_framework-0.2.0.dist-info/WHEEL
cogsol_framework-0.2.0.dist-info/entry_points.txt
cogsol_framework-0.2.0.dist-info/top_level.txt
cogsol_framework-0.2.0.dist-info/RECORD
