Metadata-Version: 2.4
Name: cogsol-framework
Version: 0.2.0
Summary: CogSol agent-first framework (alpha)
Author: Cognitive Solutions
License: MIT
Project-URL: Homepage, https://github.com/Pyxis-Cognitive-Solutions/cogsol-framework
Project-URL: Documentation, https://github.com/Pyxis-Cognitive-Solutions/cogsol-framework#readme
Project-URL: Repository, https://github.com/Pyxis-Cognitive-Solutions/cogsol-framework.git
Project-URL: Issues, https://github.com/Pyxis-Cognitive-Solutions/cogsol-framework/issues
Project-URL: Changelog, https://github.com/Pyxis-Cognitive-Solutions/cogsol-framework/blob/main/CHANGELOG.md
Keywords: ai,agents,llm,framework,assistant,chatbot
Classifier: Development Status :: 3 - Alpha
Classifier: Intended Audience :: Developers
Classifier: License :: OSI Approved :: MIT License
Classifier: Operating System :: OS Independent
Classifier: Programming Language :: Python :: 3
Classifier: Programming Language :: Python :: 3.9
Classifier: Programming Language :: Python :: 3.10
Classifier: Programming Language :: Python :: 3.11
Classifier: Programming Language :: Python :: 3.12
Classifier: Topic :: Scientific/Engineering :: Artificial Intelligence
Classifier: Topic :: Software Development :: Libraries :: Application Frameworks
Classifier: Typing :: Typed
Requires-Python: >=3.9
License-File: LICENSE
Provides-Extra: dev
Requires-Dist: pytest>=7.0; extra == "dev"
Requires-Dist: pytest-cov>=4.0; extra == "dev"
Requires-Dist: black>=23.0; extra == "dev"
Requires-Dist: ruff>=0.1.0; extra == "dev"
Requires-Dist: mypy>=1.0; extra == "dev"
Dynamic: license-file
